{
  "name": "Install GP - Beta",
  "script_path": "/opt/.gentooplayer/web/scripts/gp_install.sh",
  "description": "**Install Gentooplayer on internal HD or anather usb stick** \n **Warning:** is not strictly necessary, but the advice is to keep only the HD where to install GentooPlayer connected to the PC. \n **Warning:** assumes no responsibility for the result of the use of this function. The use of this function erases all contents of the disk. \n **Warning:** Depending on the speed of the optical media and/or the CPU, the process can take a long time (even hours).",
  "working_directory": "/tmp",
  "group": "Backup/Restore/Install",
  "parameters": [
    {
      "name": "Select version to install",
      "param": "-a",
      "type": "list",
      "required": true,
      "values": [
        "GP-Embedded-BIOS",
        "GP-Embedded-UEFI",
        "GP-Xfce4-BIOS",
        "GP-xfce4-UEFI",
        "Rpi3",
        "Rpi4"
      ],
      "description": "Select version to install"
    },
    {
      "name": "Select disk",
      "param": "-b",
      "type": "list",
      "required": true,
      "values": {
        "script": "/opt/.gentooplayer/web/scripts/script/gp/gp_install.sh"
      },
      "description": "Select disk to install GP"
    }
  ]
}
